LICENSE
lexy/__init__.py
lexy/api.py
lexy/core/__init__.py
lexy/core/glossary.py
lexy/core/term.py
lexy/docs.py
lexy/readers.py
models/spaCy/en_core_web_md-3.2.0-py3-none-any.whl
lexy-0.1.0.dist-info/LICENSE
lexy-0.1.0.dist-info/WHEEL
lexy-0.1.0.dist-info/METADATA
lexy-0.1.0.dist-info/RECORD
