Metadata-Version: 2.1
Name: lexy
Version: 0.1.0
Summary: Lexy enables you to easily build and share data dictionaries to explain and document your data terminology using code.
Home-page: https://github.com/aminekaabachi/lexy
License: MIT
Keywords: data-dictionary,data-catalog,data-governance,documentation
Author: Amine Kaabachi
Author-email: ping@kaabachi.io
Requires-Python: >=3.7.1,<4.0.0
Classifier: Development Status :: 1 - Planning
Classifier: License :: OSI Approved :: MIT License
Classifier: Natural Language :: English
Classifier: Programming Language :: Python :: 3
Classifier: Programming Language :: Python :: 3.10
Classifier: Programming Language :: Python :: 3.8
Classifier: Programming Language :: Python :: 3.9
Classifier: Topic :: Documentation
Classifier: Topic :: Scientific/Engineering :: Artificial Intelligence
Classifier: Topic :: Software Development :: Documentation
Classifier: Topic :: Software Development :: Libraries :: Python Modules
Classifier: Topic :: Utilities
Provides-Extra: SQLAlchemy
Provides-Extra: pyspark
Requires-Dist: cattrs (>=1.10.0,<2.0.0)
Requires-Dist: pandas (>=1.3.5,<2.0.0)
Requires-Dist: spacy (>=3.2.1,<4.0.0)
Project-URL: Repository, https://github.com/aminekaabachi/lexy
